COPYING
NEWS
setup.cfg
setup.py
LinkExchange.egg-info/PKG-INFO
LinkExchange.egg-info/SOURCES.txt
LinkExchange.egg-info/dependency_links.txt
LinkExchange.egg-info/entry_points.txt
LinkExchange.egg-info/namespace_packages.txt
LinkExchange.egg-info/requires.txt
LinkExchange.egg-info/top_level.txt
linkexchange/__init__.py
linkexchange/config.py
linkexchange/db_drivers.py
linkexchange/formatters.py
linkexchange/platform.py
linkexchange/tests.py
linkexchange/utils.py
linkexchange/clients/__init__.py
linkexchange/clients/base.py
linkexchange/clients/linkfeed.py
linkexchange/clients/sape.py
linkexchange/clients/trustlink.py
linkexchange/commands/__init__.py
linkexchange/commands/lxrefresh.py
tests/__init__.py
tests/test_clients.py
tests/test_db_drivers.py
tests/test_doctests.py
tests/test_platform.py